model_connector/__init__.py
model_connector/common.py
model_connector/matrix_utils.py
model_connector/read_ffb.py
model_connector/tc_matrix.py
model_connector/tc_matrix_dll.py
model_connector/write_ffb.py
model_connector-0.0.4.dist-info/METADATA
model_connector-0.0.4.dist-info/WHEEL
model_connector-0.0.4.dist-info/licenses/LICENSE
model_connector-0.0.4.dist-info/RECORD
