Metadata-Version: 2.4
Name: model_connector
Version: 0.0.4
Summary: Library for connection of TransCAD data files to Python
Author: Sean McAtee
License-File: LICENSE
Classifier: Operating System :: Microsoft :: Windows
Classifier: Programming Language :: Python :: 3
Requires-Python: >=3.11
Requires-Dist: numpy
Requires-Dist: pandas>=1.5.3
Provides-Extra: dev
Requires-Dist: black; extra == 'dev'
Requires-Dist: jupyterlab; extra == 'dev'
Requires-Dist: pytest; extra == 'dev'
Requires-Dist: pytest-cov; extra == 'dev'
